afiz_speech_text/__init__.py
afiz_speech_text/_modidx.py
afiz_speech_text/assemblyai.py
assembly_ai_plus/__init__.py
assembly_ai_plus/_modidx.py
assembly_ai_plus/assemblyai.py
assembly_ai_plus-0.0.11.dist-info/LICENSE
assembly_ai_plus-0.0.11.dist-info/METADATA
assembly_ai_plus-0.0.11.dist-info/WHEEL
assembly_ai_plus-0.0.11.dist-info/entry_points.txt
assembly_ai_plus-0.0.11.dist-info/top_level.txt
assembly_ai_plus-0.0.11.dist-info/RECORD
